maioffice/__init__.py
maioffice/excel.py
maioffice/word.py
maioffice-0.0.6.dist-info/LICENSE
maioffice-0.0.6.dist-info/METADATA
maioffice-0.0.6.dist-info/WHEEL
maioffice-0.0.6.dist-info/top_level.txt
maioffice-0.0.6.dist-info/RECORD
