Metadata-Version: 2.1
Name: maioffice
Version: 0.0.6
Summary: maishu's office package
Home-page: https://blog.qingke.me
Author: maishu
Author-email: maishucoder@gmail.com
License: UNKNOWN
Platform: UNKNOWN
Classifier: Programming Language :: Python :: 3
Classifier: License :: OSI Approved :: MIT License
Classifier: Operating System :: OS Independent
Requires-Python: >=3.6
Requires-Dist: openpyxl
Requires-Dist: python-docx
